{
  "id": "10012001-1007-11bf-f2c6-56506f415278",
  "homeTeam": {
    "id": "10403410-997c-9c75-256b-3b012f468bd0",
    "currentLogo": "https://static.www.nfl.com/{formatInstructions}/league/api/clubs/logos/NYG",
    "fullName": "New York Giants"
  },
  "awayTeam": {
    "id": "10405110-ec3c-669e-2614-db3dc1736e95",
    "currentLogo": "https://static.www.nfl.com/{formatInstructions}/league/api/clubs/logos/WAS",
    "fullName": "Washington Commanders"
  },
  "category": "OTHER",
  "date": "2001-10-07",
  "time": "2001-10-07T09:00:00Z",
  "broadcastInfo": {
    "homeNetworkChannels": [],
    "awayNetworkChannels": [],
    "internationalWatchOptions": [],
    "streamingNetworks": [],
    "territory": null,
    "audioNetworks": [
      {
        "audience": "AUDIO_NETWORK_AUDIENCE_HOME",
        "languages": [
          "en"
        ]
      },
      {
        "audience": "AUDIO_NETWORK_AUDIENCE_AWAY",
        "languages": [
          "en"
        ]
      },
      {
        "audience": "AUDIO_NETWORK_AUDIENCE_HOME_SAP",
        "languages": [
          "es"
        ]
      },
      {
        "audience": "AUDIO_NETWORK_AUDIENCE_AWAY_SAP",
        "languages": [
          "es"
        ]
      }
    ]
  },
  "gameType": "UNSPECIFIED",
  "international": false,
  "neutralSite": false,
  "venue": {
    "id": "00082056-8646-97ec-c4f0-77894b35f674",
    "name": "Giants Stadium",
    "city": "East Rutherford",
    "country": "USA"
  },
  "season": 2001,
  "seasonType": "REG",
  "status": "SCHEDULED",
  "week": 4,
  "weekType": "REG",
  "externalIds": [
    {
      "source": "elias",
      "id": "2001100711"
    },
    {
      "source": "gamedetail",
      "id": "10160000-0177-39cc-ed1d-b5ca937e7417"
    },
    {
      "source": "gsis",
      "id": "17739"
    },
    {
      "source": "shield",
      "id": "10012001-1007-11bf-f2c6-56506f415278"
    },
    {
      "source": "slug",
      "id": "redskins-at-giants-2001-reg-4"
    }
  ],
  "ticketUrl": null,
  "ticketVendors": [],
  "extensions": [],
  "version": 1,
  "summary": {
    "gameId": "10012001-1007-11bf-f2c6-56506f415278",
    "offset": 284,
    "attendance": 78651,
    "clock": "00:34",
    "distance": 12,
    "down": 3,
    "gameBookUrl": null,
    "isGoalToGo": false,
    "isRedZone": false,
    "phase": "FINAL",
    "quarter": "END_OF_GAME",
    "startTime": null,
    "weather": "Sunny Temp: 55\u00b0 F, Humidity: 38%, Wind: NW 16 mph",
    "yardLine": "NYG 6",
    "awayTeam": {
      "teamId": "10405110-ec3c-669e-2614-db3dc1736e95",
      "hasPossession": false,
      "score": {
        "q1": 3,
        "q2": 3,
        "q3": 3,
        "q4": 0,
        "ot": 0,
        "total": 9
      },
      "timeouts": {
        "remaining": 0,
        "used": 3
      }
    },
    "homeTeam": {
      "teamId": "10403410-997c-9c75-256b-3b012f468bd0",
      "hasPossession": true,
      "score": {
        "q1": 3,
        "q2": 6,
        "q3": 0,
        "q4": 14,
        "ot": 0,
        "total": 23
      },
      "timeouts": {
        "remaining": 3,
        "used": 0
      }
    }
  },
  "driveChart": {
    "gameId": "10012001-1007-11bf-f2c6-56506f415278",
    "offset": 284,
    "drives": [
      {
        "sequence": 1,
        "teamId": "10405110-ec3c-669e-2614-db3dc1736e95",
        "startedClock": "15:00",
        "startedDescription": "Kickoff",
        "startedPlayId": null,
        "startedPlaySequenceNumber": 35.0,
        "startedQuarter": 1,
        "startedTime": null,
        "startedYardLine": "WAS 31",
        "endedClock": "13:15",
        "endedDescription": "Punt",
        "endedPlayId": null,
        "endedPlaySequenceNumber": 117.0,
        "endedQuarter": 1,
        "endedTime": null,
        "endedWithScore": false,
        "endedYardLine": "WAS 33",
        "firstDowns": 0,
        "inside20": false,
        "plays": 3,
        "timeOfPossession": "1:45",
        "totalEndedWithScore": false,
        "yardsGained": 2,
        "yardsGainedByPenalty": 0,
        "yardsGainedNet": 2
      },
      {
        "sequence": 2,
        "teamId": "10403410-997c-9c75-256b-3b012f468bd0",
        "startedClock": "13:15",
        "startedDescription": "Punt",
        "startedPlayId": null,
        "startedPlaySequenceNumber": 142.0,
        "startedQuarter": 1,
        "startedTime": null,
        "startedYardLine": "NYG 41",
        "endedClock": "11:44",
        "endedDescription": "Punt",
        "endedPlayId": null,
        "endedPlaySequenceNumber": 206.0,
        "endedQuarter": 1,
        "endedTime": null,
        "endedWithScore": false,
        "endedYardLine": "50",
        "firstDowns": 0,
        "inside20": false,
        "plays": 3,
        "timeOfPossession": "1:31",
        "totalEndedWithScore": false,
        "yardsGained": 9,
        "yardsGainedByPenalty": 0,
        "yardsGainedNet": 9
      },
      {
        "sequence": 3,
        "teamId": "10405110-ec3c-669e-2614-db3dc1736e95",
        "startedClock": "11:44",
        "startedDescription": "Punt",
        "startedPlayId": null,
        "startedPlaySequenceNumber": 229.0,
        "startedQuarter": 1,
        "startedTime": null,
        "startedYardLine": "WAS 14",
        "endedClock": "10:28",
        "endedDescription": "Punt",
        "endedPlayId": null,
        "endedPlaySequenceNumber": 312.0,
        "endedQuarter": 1,
        "endedTime": null,
        "endedWithScore": false,
        "endedYardLine": "WAS 19",
        "firstDowns": 0,
        "inside20": false,
        "plays": 3,
        "timeOfPossession": "1:16",
        "totalEndedWithScore": false,
        "yardsGained": 10,
        "yardsGainedByPenalty": -5,
        "yardsGainedNet": 5
      },
      {
        "sequence": 4,
        "teamId": "10403410-997c-9c75-256b-3b012f468bd0",
        "startedClock": "10:28",
        "startedDescription": "Punt",
        "startedPlayId": null,
        "startedPlaySequenceNumber": 337.0,
        "startedQuarter": 1,
        "startedTime": null,
        "startedYardLine": "NYG 39",
        "endedClock": "06:41",
        "endedDescription": "Field Goal",
        "endedPlayId": null,
        "endedPlaySequenceNumber": 481.0,
        "endedQuarter": 1,
        "endedTime": null,
        "endedWithScore": true,
        "endedYardLine": "WAS 32",
        "firstDowns": 2,
        "inside20": false,
        "plays": 8,
        "timeOfPossession": "3:47",
        "totalEndedWithScore": false,
        "yardsGained": 29,
        "yardsGainedByPenalty": 0,
        "yardsGainedNet": 29
      },
      {
        "sequence": 5,
        "teamId": "10405110-ec3c-669e-2614-db3dc1736e95",
        "startedClock": "06:41",
        "startedDescription": "Kickoff",
        "startedPlayId": null,
        "startedPlaySequenceNumber": 500.0,
        "startedQuarter": 1,
        "startedTime": null,
        "startedYardLine": "WAS 42",
        "endedClock": "04:58",
        "endedDescription": "Punt",
        "endedPlayId": null,
        "endedPlaySequenceNumber": 580.0,
        "endedQuarter": 1,
        "endedTime": null,
        "endedWithScore": false,
        "endedYardLine": "WAS 39",
        "firstDowns": 0,
        "inside20": false,
        "plays": 3,
        "timeOfPossession": "1:43",
        "totalEndedWithScore": false,
        "yardsGained": -3,
        "yardsGainedByPenalty": 0,
        "yardsGainedNet": -3
      },
      {
        "sequence": 6,
        "teamId": "10405110-ec3c-669e-2614-db3dc1736e95",
        "startedClock": "04:58",
        "startedDescription": "Fumble",
        "startedPlayId": null,
        "startedPlaySequenceNumber": 616.0,
        "startedQuarter": 1,
        "startedTime": null,
        "startedYardLine": "NYG 20",
        "endedClock": "03:28",
        "endedDescription": "Field Goal",
        "endedPlayId": null,
        "endedPlaySequenceNumber": 692.0,
        "endedQuarter": 1,
        "endedTime": null,
        "endedWithScore": true,
        "endedYardLine": "NYG 17",
        "firstDowns": 0,
        "inside20": true,
        "plays": 4,
        "timeOfPossession": "1:30",
        "totalEndedWithScore": false,
        "yardsGained": 3,
        "yardsGainedByPenalty": 0,
        "yardsGainedNet": 3
      },
      {
        "sequence": 7,
        "teamId": "10403410-997c-9c75-256b-3b012f468bd0",
        "startedClock": "03:28",
        "startedDescription": "Kickoff",
        "startedPlayId": null,
        "startedPlaySequenceNumber": 711.0,
        "startedQuarter": 1,
        "startedTime": null,
        "startedYardLine": "NYG 20",
        "endedClock": "02:41",
        "endedDescription": "Punt",
        "endedPlayId": null,
        "endedPlaySequenceNumber": 792.0,
        "endedQuarter": 1,
        "endedTime": null,
        "endedWithScore": false,
        "endedYardLine": "NYG 20",
        "firstDowns": 0,
        "inside20": false,
        "plays": 3,
        "timeOfPossession": "0:47",
        "totalEndedWithScore": false,
        "yardsGained": 0,
        "yardsGainedByPenalty": 0,
        "yardsGainedNet": 0
      },
      {
        "sequence": 8,
        "teamId": "10403410-997c-9c75-256b-3b012f468bd0",
        "startedClock": "02:41",
        "startedDescription": "Muffed Punt",
        "startedPlayId": null,
        "startedPlaySequenceNumber": 843.0,
        "startedQuarter": 1,
        "startedTime": null,
        "startedYardLine": "NYG 44",
        "endedClock": "01:11",
        "endedDescription": "Punt",
        "endedPlayId": null,
        "endedPlaySequenceNumber": 912.0,
        "endedQuarter": 1,
        "endedTime": null,
        "endedWithScore": false,
        "endedYardLine": "NYG 47",
        "firstDowns": 0,
        "inside20": false,
        "plays": 3,
        "timeOfPossession": "1:30",
        "totalEndedWithScore": false,
        "yardsGained": 3,
        "yardsGainedByPenalty": 0,
        "yardsGainedNet": 3
      },
      {
        "sequence": 9,
        "teamId": "10405110-ec3c-669e-2614-db3dc1736e95",
        "startedClock": "01:11",
        "startedDescription": "Punt",
        "startedPlayId": null,
        "startedPlaySequenceNumber": 929.0,
        "startedQuarter": 1,
        "startedTime": null,
        "startedYardLine": "WAS 20",
        "endedClock": "00:12",
        "endedDescription": "Fumble",
        "endedPlayId": null,
        "endedPlaySequenceNumber": 988.0,
        "endedQuarter": 1,
        "endedTime": null,
        "endedWithScore": false,
        "endedYardLine": "WAS 25",
        "firstDowns": 0,
        "inside20": false,
        "plays": 3,
        "timeOfPossession": "0:59",
        "totalEndedWithScore": false,
        "yardsGained": -6,
        "yardsGainedByPenalty": 0,
        "yardsGainedNet": -6
      },
      {
        "sequence": 10,
        "teamId": "10403410-997c-9c75-256b-3b012f468bd0",
        "startedClock": "00:12",
        "startedDescription": "Fumble",
        "startedPlayId": null,
        "startedPlaySequenceNumber": 1028.0,
        "startedQuarter": 1,
        "startedTime": null,
        "startedYardLine": "WAS 14",
        "endedClock": "14:09",
        "endedDescription": "Field Goal",
        "endedPlayId": null,
        "endedPlaySequenceNumber": 1112.0,
        "endedQuarter": 2,
        "endedTime": null,
        "endedWithScore": true,
        "endedYardLine": "WAS 8",
        "firstDowns": 0,
        "inside20": true,
        "plays": 4,
        "timeOfPossession": "1:03",
        "totalEndedWithScore": false,
        "yardsGained": 6,
        "yardsGainedByPenalty": 0,
        "yardsGainedNet": 6
      },
      {
        "sequence": 11,
        "teamId": "10405110-ec3c-669e-2614-db3dc1736e95",
        "startedClock": "14:09",
        "startedDescription": "Kickoff",
        "startedPlayId": null,
        "startedPlaySequenceNumber": 1131.0,
        "startedQuarter": 2,
        "startedTime": null,
        "startedYardLine": "WAS 46",
        "endedClock": "11:25",
        "endedDescription": "Field Goal",
        "endedPlayId": null,
        "endedPlaySequenceNumber": 1354.0,
        "endedQuarter": 2,
        "endedTime": null,
        "endedWithScore": true,
        "endedYardLine": "NYG 36",
        "firstDowns": 1,
        "inside20": false,
        "plays": 6,
        "timeOfPossession": "2:44",
        "totalEndedWithScore": false,
        "yardsGained": 13,
        "yardsGainedByPenalty": 5,
        "yardsGainedNet": 18
      },
      {
        "sequence": 12,
        "teamId": "10403410-997c-9c75-256b-3b012f468bd0",
        "startedClock": "11:25",
        "startedDescription": "Kickoff",
        "startedPlayId": null,
        "startedPlaySequenceNumber": 1373.0,
        "startedQuarter": 2,
        "startedTime": null,
        "startedYardLine": "NYG 20",
        "endedClock": "05:00",
        "endedDescription": "Fumble",
        "endedPlayId": null,
        "endedPlaySequenceNumber": 1650.0,
        "endedQuarter": 2,
        "endedTime": null,
        "endedWithScore": false,
        "endedYardLine": "WAS 46",
        "firstDowns": 3,
        "inside20": false,
        "plays": 11,
        "timeOfPossession": "6:25",
        "totalEndedWithScore": false,
        "yardsGained": 52,
        "yardsGainedByPenalty": -15,
        "yardsGainedNet": 37
      },
      {
        "sequence": 13,
        "teamId": "10405110-ec3c-669e-2614-db3dc1736e95",
        "startedClock": "05:00",
        "startedDescription": "Fumble",
        "startedPlayId": null,
        "startedPlaySequenceNumber": 1682.0,
        "startedQuarter": 2,
        "startedTime": null,
        "startedYardLine": "WAS 40",
        "endedClock": "02:21",
        "endedDescription": "Fumble",
        "endedPlayId": null,
        "endedPlaySequenceNumber": 1781.0,
        "endedQuarter": 2,
        "endedTime": null,
        "endedWithScore": false,
        "endedYardLine": "NYG 47",
        "firstDowns": 1,
        "inside20": false,
        "plays": 5,
        "timeOfPossession": "2:39",
        "totalEndedWithScore": false,
        "yardsGained": 29,
        "yardsGainedByPenalty": 0,
        "yardsGainedNet": 29
      },
      {
        "sequence": 14,
        "teamId": "10403410-997c-9c75-256b-3b012f468bd0",
        "startedClock": "02:21",
        "startedDescription": "Fumble",
        "startedPlayId": null,
        "startedPlaySequenceNumber": 1813.0,
        "startedQuarter": 2,
        "startedTime": null,
        "startedYardLine": "NYG 31",
        "endedClock": "00:40",
        "endedDescription": "Field Goal",
        "endedPlayId": null,
        "endedPlaySequenceNumber": 2058.0,
        "endedQuarter": 2,
        "endedTime": null,
        "endedWithScore": true,
        "endedYardLine": "WAS 3",
        "firstDowns": 4,
        "inside20": true,
        "plays": 7,
        "timeOfPossession": "1:41",
        "totalEndedWithScore": false,
        "yardsGained": 43,
        "yardsGainedByPenalty": 23,
        "yardsGainedNet": 66
      },
      {
        "sequence": 15,
        "teamId": "10405110-ec3c-669e-2614-db3dc1736e95",
        "startedClock": "00:40",
        "startedDescription": "Kickoff",
        "startedPlayId": null,
        "startedPlaySequenceNumber": 2077.0,
        "startedQuarter": 2,
        "startedTime": null,
        "startedYardLine": "WAS 25",
        "endedClock": "00:00",
        "endedDescription": "End of Half",
        "endedPlayId": null,
        "endedPlaySequenceNumber": 2120.0,
        "endedQuarter": 2,
        "endedTime": null,
        "endedWithScore": false,
        "endedYardLine": "WAS 25",
        "firstDowns": 0,
        "inside20": false,
        "plays": 1,
        "timeOfPossession": "0:40",
        "totalEndedWithScore": false,
        "yardsGained": 5,
        "yardsGainedByPenalty": 0,
        "yardsGainedNet": 5
      },
      {
        "sequence": 16,
        "teamId": "10403410-997c-9c75-256b-3b012f468bd0",
        "startedClock": "15:00",
        "startedDescription": "Kickoff",
        "startedPlayId": null,
        "startedPlaySequenceNumber": 2140.0,
        "startedQuarter": 3,
        "startedTime": null,
        "startedYardLine": "NYG 30",
        "endedClock": "14:43",
        "endedDescription": "Interception",
        "endedPlayId": null,
        "endedPlaySequenceNumber": 2162.0,
        "endedQuarter": 3,
        "endedTime": null,
        "endedWithScore": false,
        "endedYardLine": "NYG 30",
        "firstDowns": 0,
        "inside20": false,
        "plays": 1,
        "timeOfPossession": "0:17",
        "totalEndedWithScore": false,
        "yardsGained": 0,
        "yardsGainedByPenalty": 0,
        "yardsGainedNet": 0
      },
      {
        "sequence": 17,
        "teamId": "10405110-ec3c-669e-2614-db3dc1736e95",
        "startedClock": "14:43",
        "startedDescription": "Interception",
        "startedPlayId": null,
        "startedPlaySequenceNumber": 2186.0,
        "startedQuarter": 3,
        "startedTime": null,
        "startedYardLine": "NYG 40",
        "endedClock": "13:48",
        "endedDescription": "Punt",
        "endedPlayId": null,
        "endedPlaySequenceNumber": 2243.0,
        "endedQuarter": 3,
        "endedTime": null,
        "endedWithScore": false,
        "endedYardLine": "NYG 40",
        "firstDowns": 0,
        "inside20": false,
        "plays": 3,
        "timeOfPossession": "0:55",
        "totalEndedWithScore": false,
        "yardsGained": 0,
        "yardsGainedByPenalty": 0,
        "yardsGainedNet": 0
      },
      {
        "sequence": 18,
        "teamId": "10403410-997c-9c75-256b-3b012f468bd0",
        "startedClock": "13:48",
        "startedDescription": "Punt",
        "startedPlayId": null,
        "startedPlaySequenceNumber": 2268.0,
        "startedQuarter": 3,
        "startedTime": null,
        "startedYardLine": "NYG 12",
        "endedClock": "06:08",
        "endedDescription": "Downs",
        "endedPlayId": null,
        "endedPlaySequenceNumber": 2538.0,
        "endedQuarter": 3,
        "endedTime": null,
        "endedWithScore": false,
        "endedYardLine": "WAS 28",
        "firstDowns": 4,
        "inside20": false,
        "plays": 14,
        "timeOfPossession": "7:40",
        "totalEndedWithScore": false,
        "yardsGained": 50,
        "yardsGainedByPenalty": 0,
        "yardsGainedNet": 50
      },
      {
        "sequence": 19,
        "teamId": "10405110-ec3c-669e-2614-db3dc1736e95",
        "startedClock": "06:08",
        "startedDescription": "Downs",
        "startedPlayId": null,
        "startedPlaySequenceNumber": 2557.0,
        "startedQuarter": 3,
        "startedTime": null,
        "startedYardLine": "WAS 38",
        "endedClock": "03:29",
        "endedDescription": "Field Goal",
        "endedPlayId": null,
        "endedPlaySequenceNumber": 2733.0,
        "endedQuarter": 3,
        "endedTime": null,
        "endedWithScore": true,
        "endedYardLine": "NYG 22",
        "firstDowns": 3,
        "inside20": false,
        "plays": 7,
        "timeOfPossession": "2:39",
        "totalEndedWithScore": false,
        "yardsGained": 40,
        "yardsGainedByPenalty": 0,
        "yardsGainedNet": 40
      },
      {
        "sequence": 20,
        "teamId": "10403410-997c-9c75-256b-3b012f468bd0",
        "startedClock": "03:29",
        "startedDescription": "Kickoff",
        "startedPlayId": null,
        "startedPlaySequenceNumber": 2752.0,
        "startedQuarter": 3,
        "startedTime": null,
        "startedYardLine": "NYG 29",
        "endedClock": "12:59",
        "endedDescription": "Touchdown",
        "endedPlayId": null,
        "endedPlaySequenceNumber": 3028.0,
        "endedQuarter": 4,
        "endedTime": null,
        "endedWithScore": true,
        "endedYardLine": "WAS 1",
        "firstDowns": 5,
        "inside20": true,
        "plays": 10,
        "timeOfPossession": "5:30",
        "totalEndedWithScore": false,
        "yardsGained": 71,
        "yardsGainedByPenalty": 0,
        "yardsGainedNet": 71
      },
      {
        "sequence": 21,
        "teamId": "10405110-ec3c-669e-2614-db3dc1736e95",
        "startedClock": "12:59",
        "startedDescription": "Kickoff",
        "startedPlayId": null,
        "startedPlaySequenceNumber": 3044.0,
        "startedQuarter": 4,
        "startedTime": null,
        "startedYardLine": "WAS 31",
        "endedClock": "11:28",
        "endedDescription": "Interception",
        "endedPlayId": null,
        "endedPlaySequenceNumber": 3148.0,
        "endedQuarter": 4,
        "endedTime": null,
        "endedWithScore": false,
        "endedYardLine": "NYG 17",
        "firstDowns": 1,
        "inside20": true,
        "plays": 4,
        "timeOfPossession": "1:31",
        "totalEndedWithScore": false,
        "yardsGained": 52,
        "yardsGainedByPenalty": 0,
        "yardsGainedNet": 52
      },
      {
        "sequence": 22,
        "teamId": "10403410-997c-9c75-256b-3b012f468bd0",
        "startedClock": "11:28",
        "startedDescription": "Interception",
        "startedPlayId": null,
        "startedPlaySequenceNumber": 3168.0,
        "startedQuarter": 4,
        "startedTime": null,
        "startedYardLine": "NYG 20",
        "endedClock": "04:49",
        "endedDescription": "Interception",
        "endedPlayId": null,
        "endedPlaySequenceNumber": 3428.0,
        "endedQuarter": 4,
        "endedTime": null,
        "endedWithScore": false,
        "endedYardLine": "WAS 45",
        "firstDowns": 3,
        "inside20": false,
        "plays": 10,
        "timeOfPossession": "6:39",
        "totalEndedWithScore": false,
        "yardsGained": 50,
        "yardsGainedByPenalty": -15,
        "yardsGainedNet": 35
      },
      {
        "sequence": 23,
        "teamId": "10405110-ec3c-669e-2614-db3dc1736e95",
        "startedClock": "04:49",
        "startedDescription": "Interception",
        "startedPlayId": null,
        "startedPlaySequenceNumber": 3458.0,
        "startedQuarter": 4,
        "startedTime": null,
        "startedYardLine": "WAS 33",
        "endedClock": "03:42",
        "endedDescription": "Punt",
        "endedPlayId": null,
        "endedPlaySequenceNumber": 3515.0,
        "endedQuarter": 4,
        "endedTime": null,
        "endedWithScore": false,
        "endedYardLine": "WAS 33",
        "firstDowns": 0,
        "inside20": false,
        "plays": 3,
        "timeOfPossession": "1:07",
        "totalEndedWithScore": false,
        "yardsGained": 0,
        "yardsGainedByPenalty": 0,
        "yardsGainedNet": 0
      },
      {
        "sequence": 24,
        "teamId": "10403410-997c-9c75-256b-3b012f468bd0",
        "startedClock": "03:42",
        "startedDescription": "Punt",
        "startedPlayId": null,
        "startedPlaySequenceNumber": 3534.0,
        "startedQuarter": 4,
        "startedTime": null,
        "startedYardLine": "NYG 11",
        "endedClock": "03:07",
        "endedDescription": "Punt",
        "endedPlayId": null,
        "endedPlaySequenceNumber": 3628.0,
        "endedQuarter": 4,
        "endedTime": null,
        "endedWithScore": false,
        "endedYardLine": "NYG 9",
        "firstDowns": 0,
        "inside20": false,
        "plays": 3,
        "timeOfPossession": "0:35",
        "totalEndedWithScore": false,
        "yardsGained": -2,
        "yardsGainedByPenalty": 0,
        "yardsGainedNet": -2
      },
      {
        "sequence": 25,
        "teamId": "10405110-ec3c-669e-2614-db3dc1736e95",
        "startedClock": "03:07",
        "startedDescription": "Punt",
        "startedPlayId": null,
        "startedPlaySequenceNumber": 3664.0,
        "startedQuarter": 4,
        "startedTime": null,
        "startedYardLine": "WAS 28",
        "endedClock": "02:57",
        "endedDescription": "Interception",
        "endedPlayId": null,
        "endedPlaySequenceNumber": 3664.0,
        "endedQuarter": 4,
        "endedTime": null,
        "endedWithScore": false,
        "endedYardLine": "WAS 28",
        "firstDowns": 0,
        "inside20": false,
        "plays": 1,
        "timeOfPossession": "0:10",
        "totalEndedWithScore": false,
        "yardsGained": 0,
        "yardsGainedByPenalty": 0,
        "yardsGainedNet": 0
      },
      {
        "sequence": 26,
        "teamId": "10405110-ec3c-669e-2614-db3dc1736e95",
        "startedClock": "02:57",
        "startedDescription": "Kickoff",
        "startedPlayId": null,
        "startedPlaySequenceNumber": 3700.0,
        "startedQuarter": 4,
        "startedTime": null,
        "startedYardLine": "WAS 42",
        "endedClock": "01:06",
        "endedDescription": "Downs",
        "endedPlayId": null,
        "endedPlaySequenceNumber": 3939.0,
        "endedQuarter": 4,
        "endedTime": null,
        "endedWithScore": false,
        "endedYardLine": "NYG 12",
        "firstDowns": 3,
        "inside20": true,
        "plays": 9,
        "timeOfPossession": "1:51",
        "totalEndedWithScore": false,
        "yardsGained": 36,
        "yardsGainedByPenalty": 14,
        "yardsGainedNet": 50
      },
      {
        "sequence": 27,
        "teamId": "10403410-997c-9c75-256b-3b012f468bd0",
        "startedClock": "01:06",
        "startedDescription": "Downs",
        "startedPlayId": 4002,
        "startedPlaySequenceNumber": 3960.0,
        "startedQuarter": 4,
        "startedTime": null,
        "startedYardLine": "NYG 8",
        "endedClock": "00:00",
        "endedDescription": "End of Game",
        "endedPlayId": 4002,
        "endedPlaySequenceNumber": 4002.0,
        "endedQuarter": 4,
        "endedTime": null,
        "endedWithScore": false,
        "endedYardLine": "NYG 7",
        "firstDowns": 0,
        "inside20": false,
        "plays": 2,
        "timeOfPossession": "1:06",
        "totalEndedWithScore": false,
        "yardsGained": -2,
        "yardsGainedByPenalty": 0,
        "yardsGainedNet": -2
      }
    ],
    "plays": [
      {
        "playId": 1,
        "clockTime": null,
        "down": 0,
        "driveNetYards": 0,
        "drivePlayCount": 0,
        "driveSequence": 0,
        "driveTimeOfPossession": null,
        "nextPlayType": "PLAY_FROM_SCRIMMAGE",
        "nextPlayIsGoalToGo": false,
        "prePlayByPlay": "WAS - NYG",
        "playDeleted": false,
        "playDescription": "GAME",
        "playDescriptionWithJerseyNumbers": "GAME",
        "playEndTime": null,
        "playIsEndOfQuarter": false,
        "playIsGoalToGo": false,
        "playScored": false,
        "playSequenceNumber": 1.0,
        "playStartTime": null,
        "playType": "GAME_START",
        "quarter": 1,
        "scoringPlayType": "UNSPECIFIED",
        "scoringTeamId": null,
        "specialTeamsPlayType": "UNSPECIFIED",
        "yardLine": null,
        "yardsGained": 0,
        "yardsRemaining": 0,
        "stats": []
      },
      {
        "playId": 4002,
        "clockTime": null,
        "down": 0,
        "driveNetYards": -2,
        "drivePlayCount": 2,
        "driveSequence": 27,
        "driveTimeOfPossession": "1:06",
        "nextPlayType": "PLAY_FROM_SCRIMMAGE",
        "nextPlayIsGoalToGo": false,
        "prePlayByPlay": "END GAME",
        "playDeleted": false,
        "playDescription": "END GAME",
        "playDescriptionWithJerseyNumbers": "END GAME",
        "playEndTime": null,
        "playIsEndOfQuarter": true,
        "playIsGoalToGo": false,
        "playScored": false,
        "playSequenceNumber": 4002.0,
        "playStartTime": null,
        "playType": "END_GAME",
        "quarter": 4,
        "scoringPlayType": "UNSPECIFIED",
        "scoringTeamId": null,
        "specialTeamsPlayType": "UNSPECIFIED",
        "yardLine": null,
        "yardsGained": 0,
        "yardsRemaining": 0,
        "stats": []
      }
    ],
    "scoringSummaries": [
      {
        "sequence": 1,
        "awayScore": 0,
        "clockTime": "06:41",
        "homeScore": 3,
        "patPlayId": 0,
        "playDescription": "M. Andersen 50 yd. Field Goal (8-29, 3:47)",
        "quarter": 1,
        "scoreType": "FIELD_GOAL",
        "scoringPlayId": 481,
        "scoringTeamId": "10403410-997c-9c75-256b-3b012f468bd0"
      },
      {
        "sequence": 2,
        "awayScore": 3,
        "clockTime": "03:28",
        "homeScore": 3,
        "patPlayId": 0,
        "playDescription": "B.Conway 35 yd. Field Goal (4-3, 1:30)",
        "quarter": 1,
        "scoreType": "FIELD_GOAL",
        "scoringPlayId": 692,
        "scoringTeamId": "10405110-ec3c-669e-2614-db3dc1736e95"
      },
      {
        "sequence": 3,
        "awayScore": 3,
        "clockTime": "14:09",
        "homeScore": 6,
        "patPlayId": 0,
        "playDescription": "M. Andersen 26 yd. Field Goal (4-6, 1:03)",
        "quarter": 2,
        "scoreType": "FIELD_GOAL",
        "scoringPlayId": 1112,
        "scoringTeamId": "10403410-997c-9c75-256b-3b012f468bd0"
      },
      {
        "sequence": 4,
        "awayScore": 6,
        "clockTime": "11:25",
        "homeScore": 6,
        "patPlayId": 0,
        "playDescription": "B.Conway 55 yd. Field Goal (6-18, 2:44)",
        "quarter": 2,
        "scoreType": "FIELD_GOAL",
        "scoringPlayId": 1354,
        "scoringTeamId": "10405110-ec3c-669e-2614-db3dc1736e95"
      },
      {
        "sequence": 5,
        "awayScore": 6,
        "clockTime": "00:40",
        "homeScore": 9,
        "patPlayId": 0,
        "playDescription": "M. Andersen 22 yd. Field Goal (7-66, 1:41)",
        "quarter": 2,
        "scoreType": "FIELD_GOAL",
        "scoringPlayId": 2058,
        "scoringTeamId": "10403410-997c-9c75-256b-3b012f468bd0"
      },
      {
        "sequence": 6,
        "awayScore": 9,
        "clockTime": "03:29",
        "homeScore": 9,
        "patPlayId": 0,
        "playDescription": "B.Conway 41 yd. Field Goal (7-40, 2:39)",
        "quarter": 3,
        "scoreType": "FIELD_GOAL",
        "scoringPlayId": 2733,
        "scoringTeamId": "10405110-ec3c-669e-2614-db3dc1736e95"
      },
      {
        "sequence": 7,
        "awayScore": 9,
        "clockTime": "12:59",
        "homeScore": 16,
        "patPlayId": 3028,
        "playDescription": "D. Campbell 1 yd. pass from K. Collins (M. Andersen kick) (10-71, 5:30)",
        "quarter": 4,
        "scoreType": "TOUCHDOWN",
        "scoringPlayId": 3011,
        "scoringTeamId": "10403410-997c-9c75-256b-3b012f468bd0"
      },
      {
        "sequence": 8,
        "awayScore": 9,
        "clockTime": "02:57",
        "homeScore": 23,
        "patPlayId": 3684,
        "playDescription": "J. Sehorn 34 yd. interception return (M. Andersen kick)",
        "quarter": 4,
        "scoreType": "TOUCHDOWN",
        "scoringPlayId": 3664,
        "scoringTeamId": "10403410-997c-9c75-256b-3b012f468bd0"
      }
    ]
  },
  "replays": null,
  "taggedVideos": null,
  "awayTeamStandings": null,
  "homeTeamStandings": null
}